<?xml version="1.0"?>
<MasterPredefinedSettings>
  
  <Profile>
    <Name>OC1</Name>
    <CPUOCEnabled>True</CPUOCEnabled>
    <MEMOCEnabled>False</MEMOCEnabled>
    <XMPProfile></XMPProfile>
    <GPUOCEnabled>True</GPUOCEnabled>
    <ThermalProfile>Normal</ThermalProfile>
  </Profile>
  
  <Profile>
    <Name>OC2</Name>
    <CPUOCEnabled>True</CPUOCEnabled>
    <MEMOCEnabled>True</MEMOCEnabled>
    <XMPProfile>XMP1</XMPProfile>
    <GPUOCEnabled>True</GPUOCEnabled>
    <ThermalProfile>Normal</ThermalProfile>
  </Profile>
  
</MasterPredefinedSettings>


